<?xml version="1.0" encoding="utf-8" ?>
<dwsync>
<file name="jquery.js" server="ftp.christianpetri.ch//kontakt.christianpetri.ch/" local="131017316181007669" remote="131017060800000000" Dst="1" />
<file name="jump.js" server="ftp.christianpetri.ch//kontakt.christianpetri.ch/" local="131017771778225075" remote="131017450200000000" Dst="1" />
<file name="js.js" server="ftp.christianpetri.ch/kontakt.christianpetri.ch/" local="131019196446009199" remote="131018910600000000" Dst="1" />
<file name="jump.js" server="ftp.christianpetri.ch/kontakt.christianpetri.ch/" local="131019137081671309" remote="131018813400000000" Dst="1" />
<file name="jquery.js" server="ftp.christianpetri.ch/kontakt.christianpetri.ch/" local="131019137081601250" remote="131018813400000000" Dst="1" />
<file name="jump-multi.js" server="ftp.christianpetri.ch/kontakt.christianpetri.ch/" local="131020060583142390" remote="131019736200000000" Dst="1" />
<file name="effect-explode.js" server="ftp.christianpetri.ch/kontakt.christianpetri.ch/" local="131019251429164927" remote="131018938200000000" Dst="1" />
<file name="jquery-ui.min.js" server="ftp.christianpetri.ch/kontakt.christianpetri.ch/" local="131019848527021648" remote="131018970000000000" Dst="1" />
</dwsync>