<?xml version="1.0" encoding="utf-8" ?>
<dwsync>
<file name="favicon.gif" server="ftp.christianpetri.ch//kontakt.christianpetri.ch/" local="131022894343497316" remote="131019288000000000" Dst="1" />
<file name="favicon.ico" server="ftp.christianpetri.ch//kontakt.christianpetri.ch/" local="131022894352711738" remote="131019288000000000" Dst="1" />
<file name="index.php" server="C:/xampp/htdocs/christianpetri.ch/" local="131026773102311486" remote="131026773100000000" Dst="1" />
<file name="favicon.gif" server="ftp.christianpetri.ch/kontakt.christianpetri.ch/" local="131025009599995005" remote="131024851200000000" Dst="1" />
<file name="favicon.ico" server="ftp.christianpetri.ch/kontakt.christianpetri.ch/" local="131025009600005021" remote="131024851200000000" Dst="1" />
<file name="galerie.php" server="C:/xampp/htdocs/christianpetri.ch/" local="131025138543367797" remote="131025138540000000" Dst="1" />
<file name="galerie.php" server="ftp.christianpetri.ch/kontakt.christianpetri.ch/" local="131025138543367797" remote="131024850000000000" Dst="1" />
<file name="index.php" server="ftp.christianpetri.ch/kontakt.christianpetri.ch/" local="131026775035008253" remote="131026486200000000" Dst="1" />
<file name="jump.php" server="ftp.christianpetri.ch/kontakt.christianpetri.ch/" local="131026787564491453" remote="131026499400000000" Dst="1" />
<file name="jump.php" server="C:/xampp/htdocs/christianpetri.ch/" local="131026795974807221" remote="131026795970000000" Dst="1" />
<file name="purejavascript.php" server="ftp.christianpetri.ch/kontakt.christianpetri.ch/" local="131025009600695493" remote="131024743800000000" Dst="1" />
<file name="empfangen.php" server="C:/xampp/htdocs/christianpetri.ch/" local="131026756440615800" remote="131026756440000000" Dst="1" />
<file name="empfangen.php" server="ftp.christianpetri.ch/kontakt.christianpetri.ch/" local="131026756440615800" remote="131026467600000000" Dst="1" />
<file name="user.php" server="C:/xampp/htdocs/christianpetri.ch/" local="131026982539983727" remote="131026982530000000" Dst="1" />
<file name="user.php" server="ftp.christianpetri.ch/kontakt.christianpetri.ch/" local="131026952320313304" remote="131026663800000000" Dst="1" />
<file name="userloggedin.php" server="C:/xampp/htdocs/christianpetri.ch/" local="131026853102809812" remote="131026853100000000" Dst="1" />
<file name="usernew.php" server="C:/xampp/htdocs/christianpetri.ch/" local="131026914769731417" remote="131026914760000000" Dst="1" />
<file name="usernew.php" server="ftp.christianpetri.ch/kontakt.christianpetri.ch/" local="131026914769731417" remote="131026628400000000" Dst="1" />
<file name="userloggedin.php" server="ftp.christianpetri.ch/kontakt.christianpetri.ch/" local="131026853102809812" remote="131026615200000000" Dst="1" />
</dwsync>